solposx/__init__.py
solposx/tools.py
solposx/refraction/__init__.py
solposx/refraction/archer.py
solposx/refraction/bennett.py
solposx/refraction/hughes.py
solposx/refraction/michalsky.py
solposx/refraction/sg2.py
solposx/refraction/spa.py
solposx/solarposition/__init__.py
solposx/solarposition/iqbal.py
solposx/solarposition/michalsky.py
solposx/solarposition/nasa_horizons.py
solposx/solarposition/noaa.py
solposx/solarposition/psa.py
solposx/solarposition/sg2.py
solposx/solarposition/skyfield.py
solposx/solarposition/spa.py
solposx/solarposition/usno.py
solposx/solarposition/walraven.py
solposx-1.0.1.dist-info/licenses/LICENSE
solposx-1.0.1.dist-info/METADATA
solposx-1.0.1.dist-info/WHEEL
solposx-1.0.1.dist-info/top_level.txt
solposx-1.0.1.dist-info/RECORD
